polare/__init__.py
polare/_numpy_ufunc_overrides.py
polare/_stroke_utils.py
polare/interpolant.py
polare/stroke.py
polare-0.1.0.dist-info/LICENSE.txt
polare-0.1.0.dist-info/METADATA
polare-0.1.0.dist-info/WHEEL
polare-0.1.0.dist-info/top_level.txt
polare-0.1.0.dist-info/RECORD
