Metadata-Version: 2.1
Name: polare
Version: 0.1.0
Summary: Kernels for continuous data transformations.
Home-page: https://github.com/JaiWillems/polare
Author: Jai Willems
Author-email: jai52h@hotmail.com
License: BSD-3-Clause
Platform: UNKNOWN
Classifier: Development Status :: 5 - Production/Stable
Classifier: Intended Audience :: Science/Research
Classifier: Programming Language :: Python
Classifier: License :: OSI Approved :: BSD License
Classifier: Operating System :: OS Independent
Classifier: Topic :: Scientific/Engineering
License-File: LICENSE.txt
Requires-Dist: numpy
Requires-Dist: scipy
